common/__init__.py
common/types/vmmetrics.py
centrality_common-0.0.1.dist-info/WHEEL
centrality_common-0.0.1.dist-info/METADATA
centrality_common-0.0.1.dist-info/RECORD
